aiml_b/lab3/q3/q3.v
module q3(a, b, c, d, f);
    input a, b, c, d;
    output f;
    assign f = (~(a)|d)&(a|(~c)|d);
    
endmodule

aiml_b/lab3/q3/q3_tb.v
`timescale 1ns/1ps
`include "q3.v"

module q3_tb;
    reg a_t, b_t, c_t, d_t;
    wire f_t;


    q3 q3 (a_t, b_t,c_t,d_t,f_t);

    initial begin
        $dumpfile("q3_tb.vcd");
        $dumpvars(0, q3_tb);
a_t=0; b_t=0; c_t=0; d_t=0; #5;
a_t=0; b_t=0; c_t=0; d_t=1; #5;
a_t=0; b_t=0; c_t=1; d_t=0; #5;
a_t=0; b_t=0; c_t=1; d_t=1; #5;
a_t=0; b_t=1; c_t=0; d_t=0; #5;
a_t=0; b_t=1; c_t=0; d_t=1; #5;
a_t=0; b_t=1; c_t=1; d_t=0; #5;
a_t=0; b_t=1; c_t=1; d_t=1; #5;
a_t=1; b_t=0; c_t=0; d_t=0; #5;
a_t=1; b_t=0; c_t=0; d_t=1; #5;
a_t=1; b_t=0; c_t=1; d_t=0; #5;
a_t=1; b_t=0; c_t=1; d_t=1; #5;
a_t=1; b_t=1; c_t=0; d_t=0; #5;
a_t=1; b_t=1; c_t=0; d_t=1; #5;
a_t=1; b_t=1; c_t=1; d_t=0; #5;
a_t=1; b_t=1; c_t=1; d_t=1; #5;

        $display("Test complete");
        $finish;
    end
endmodule

aiml_b/lab3/q3/q3_tb.vcd
$date
	Mon Aug 11 15:52:56 2025
$end
$version
	Icarus Verilog
$end
$timescale
	1ps
$end
$scope module q3_tb $end
$var wire 1 ! f_t $end
$var reg 1 " a_t $end
$var reg 1 # b_t $end
$var reg 1 $ c_t $end
$var reg 1 % d_t $end
$scope module q3 $end
$var wire 1 " a $end
$var wire 1 # b $end
$var wire 1 $ c $end
$var wire 1 % d $end
$var wire 1 ! f $end
$upscope $end
$upscope $end
$enddefinitions $end
#0
$dumpvars
0%
0$
0#
0"
1!
$end
#5000
1%
#10000
0!
0%
1$
#15000
1!
1%
#20000
1!
0%
0$
1#
#25000
1%
#30000
0!
0%
1$
#35000
1!
1%
#40000
0!
0%
0$
0#
1"
#45000
1!
1%
#50000
0!
0%
1$
#55000
1!
1%
#60000
0!
0%
0$
1#
#65000
1!
1%
#70000
0!
0%
1$
#75000
1!
1%
