DISL Lab/Lab 2/q3/q3.v
module q3(f, x1, x2, x3, x4);
	input x1, x2, x3, x4;
	output f;
	and(o1, x1, x2, x4);
	and(o2, x1, x3, x4);
	and(o3, x1, x2, x3);
	and(o4, x2, x3, x4);
	or(f, o1, o2, o3, o4);
endmodule

DISL Lab/Lab 2/q3/q3_tb.v
`timescale 1ns/1ns
`include "q3.v"

module q3_tb();
reg A, B, C, D;
wire F;

q3 que3(F, A, B, C, D);
initial
begin
	$dumpfile("q3.vcd");
	$dumpvars(0, q3_tb);
	
	A = 1'b0; B = 1'b0; C = 1'b0; D = 1'b0;
	#20;
	A = 1'b0; B = 1'b0; C = 1'b0; D= 1'b1;
	#20;
	A = 1'b0; B = 1'b0; C = 1'b1; D = 1'b0;
	#20;
	A = 1'b0; B = 1'b0; C = 1'b1; D = 1'b1;
	#20;
	A = 1'b0; B = 1'b1; C = 1'b0; D = 1'b0;
	#20;
	A = 1'b0; B = 1'b1; C = 1'b0; D = 1'b1;
	#20;
	A = 1'b0; B = 1'b1; C = 1'b1; D = 1'b0;
	#20;
	A = 1'b0; B = 1'b1; C = 1'b1; D = 1'b1;
	#20;
	A = 1'b1; B = 1'b0; C = 1'b0; D = 1'b0;
	#20;
	A = 1'b1; B = 1'b0; C = 1'b0; D = 1'b1;
	#20;
	A = 1'b1; B = 1'b0; C = 1'b1; D = 1'b0;
	#20;
	A = 1'b1; B = 1'b0; C = 1'b1; D = 1'b1;
	#20;
	A = 1'b1; B = 1'b1; C = 1'b0; D = 1'b0;
	#20;
	A = 1'b1; B = 1'b1; C = 1'b0; D = 1'b1;
	#20;
	A = 1'b1; B = 1'b1; C = 1'b1; D = 1'b0;
	#20;
	A = 1'b1; B = 1'b1; C = 1'b1; D = 1'b1;
	#20;
	
	$display("please work");
end
endmodule

DISL Lab/Lab 2/q3/q3.vcd
$date
	Tue Aug  5 16:01:26 2025
$end
$version
	Icarus Verilog
$end
$timescale
	1ns
$end
$scope module q3_tb $end
$var wire 1 ! F $end
$var reg 1 " A $end
$var reg 1 # B $end
$var reg 1 $ C $end
$var reg 1 % D $end
$scope module que3 $end
$var wire 1 ! f $end
$var wire 1 & o1 $end
$var wire 1 ' o2 $end
$var wire 1 ( o3 $end
$var wire 1 ) o4 $end
$var wire 1 " x1 $end
$var wire 1 # x2 $end
$var wire 1 $ x3 $end
$var wire 1 % x4 $end
$upscope $end
$upscope $end
$enddefinitions $end
#0
$dumpvars
0)
0(
0'
0&
0%
0$
0#
0"
0!
$end
#20
1%
#40
0%
1$
#60
1%
#80
0%
0$
1#
#100
1%
#120
0%
1$
#140
1!
1)
1%
#160
0!
0)
0%
0$
0#
1"
#180
1%
#200
0%
1$
#220
1!
1'
1%
#240
0!
0'
0%
0$
1#
#260
1!
1&
1%
#280
0&
1(
0%
1$
#300
1&
1'
1)
1%
