DISL Lab/Lab 1/q1/q1_struct.v
module q1_struct (f, a, b, c, d);
	input a, b, c, d;
	output f;
	and(o1, a, b);
	and(o2, a, b);
	or(o3, o1, c);
	or(o4, o2, c);
	not(o3_, o3);
	and(o5, o3_, d);
	or(o6, d, o4);
	and(f, o5, o6);
endmodule

DISL Lab/Lab 1/q1/q1_tb.v
`timescale 1ns/1ns
`include "q1_struct.v"

module q1_tb();
reg a, b, c, d;
wire o1, o2, o3, o4, o3_, o5, o6, f;

q1_struct q1(f, a, b, c, d);
initial
begin
	$dumpfile("q1_struct.vcd");
	$dumpvars(0, q1_tb);
	
	a = 1'b0; b = 1'b0; c = 1'b0; d = 1'b0;
	#20;
	a = 1'b0; b = 1'b0; c = 1'b0; d = 1'b1;
	#20;
	a = 1'b0; b = 1'b0; c = 1'b1; d = 1'b0;
	#20;
	a = 1'b0; b = 1'b0; c = 1'b1; d = 1'b1;
	#20;
	a = 1'b0; b = 1'b1; c = 1'b0; d = 1'b0;
	#20;
	a = 1'b0; b = 1'b1; c = 1'b0; d = 1'b1;
	#20;
	a = 1'b0; b = 1'b1; c = 1'b1; d = 1'b0;
	#20;
	a = 1'b0; b = 1'b1; c = 1'b1; d = 1'b1;
	#20;
	a = 1'b1; b = 1'b0; c = 1'b0; d = 1'b0;
	#20;
	a = 1'b1; b = 1'b0; c = 1'b0; d = 1'b1;
	#20;
	a = 1'b1; b = 1'b0; c = 1'b1; d = 1'b0;
	#20;
	a = 1'b1; b = 1'b0; c = 1'b1; d = 1'b1;
	#20;
	a = 1'b1; b = 1'b1; c = 1'b0; d = 1'b0;
	#20;
	a = 1'b1; b = 1'b1; c = 1'b0; d = 1'b1;
	#20;
	a = 1'b1; b = 1'b1; c = 1'b1; d = 1'b0;
	#20;
	a = 1'b1; b = 1'b1; c = 1'b1; d = 1'b1;
	#20;
	
	$display("please work");
end

endmodule

DISL Lab/Lab 1/q1/q1_behav.vcd
$date
	Tue Aug  5 14:43:24 2025
$end
$version
	Icarus Verilog
$end
$timescale
	1ns
$end
$scope module q1_tb $end
$var wire 1 ! f $end
$var reg 1 " a $end
$var reg 1 # b $end
$var reg 1 $ c $end
$var reg 1 % d $end
$scope module q1 $end
$var wire 1 " a $end
$var wire 1 # b $end
$var wire 1 $ c $end
$var wire 1 % d $end
$var wire 1 ! f $end
$upscope $end
$upscope $end
$enddefinitions $end
#0
$dumpvars
0%
0$
0#
0"
0!
$end
#20
1!
1%
#40
0!
0%
1$
#60
1%
#80
0%
0$
1#
#100
1!
1%
#120
0!
0%
1$
#140
1%
#160
0%
0$
0#
1"
#180
1!
1%
#200
0!
0%
1$
#220
1%
#240
0%
0$
1#
#260
1%
#280
0%
1$
#300
1%
