DISL Lab/Lab 3/q2/q2.v
module q2(F, A, B, C, D);
	input A, B, C, D;
	output F;
	nor n1(Dn, D, D);
	nor n2(o1, B, D);
	nor n3(o2, B, C);
	nor n4(o3, A, C, Dn);
	nor n5(o4, o3, o2, o1);
	nor n6(F, o4, o4);
endmodule

DISL Lab/Lab 3/q2/q2_tb.v
`timescale 1ns/1ns
`include "q2.v"

module q2_tb();
reg A, B, C, D;
wire F;
q2 q2 (F, A, B, C, D);
initial
begin
	$dumpfile("q2.vcd");
	$dumpvars(0, q2_tb);
	
	A = 1'b0; B = 1'b0; C = 1'b0; D = 1'b0;
	#20;
	A = 1'b0; B = 1'b0; C = 1'b0; D= 1'b1;
	#20;
	A = 1'b0; B = 1'b0; C = 1'b1; D = 1'b0;
	#20;
	A = 1'b0; B = 1'b0; C = 1'b1; D = 1'b1;
	#20;
	A = 1'b0; B = 1'b1; C = 1'b0; D = 1'b0;
	#20;
	A = 1'b0; B = 1'b1; C = 1'b0; D = 1'b1;
	#20;
	A = 1'b0; B = 1'b1; C = 1'b1; D = 1'b0;
	#20;
	A = 1'b0; B = 1'b1; C = 1'b1; D = 1'b1;
	#20;
	A = 1'b1; B = 1'b0; C = 1'b0; D = 1'b0;
	#20;
	A = 1'b1; B = 1'b0; C = 1'b0; D = 1'b1;
	#20;
	A = 1'b1; B = 1'b0; C = 1'b1; D = 1'b0;
	#20;
	A = 1'b1; B = 1'b0; C = 1'b1; D = 1'b1;
	#20;
	A = 1'b1; B = 1'b1; C = 1'b0; D = 1'b0;
	#20;
	A = 1'b1; B = 1'b1; C = 1'b0; D = 1'b1;
	#20;
	A = 1'b1; B = 1'b1; C = 1'b1; D = 1'b0;
	#20;
	A = 1'b1; B = 1'b1; C = 1'b1; D = 1'b1;
	#20;
	
	$display("please work");
end
endmodule

DISL Lab/Lab 3/q2/q2.vcd
$date
	Tue Aug 12 15:15:40 2025
$end
$version
	Icarus Verilog
$end
$timescale
	1ns
$end
$scope module q2_tb $end
$var wire 1 ! F $end
$var reg 1 " A $end
$var reg 1 # B $end
$var reg 1 $ C $end
$var reg 1 % D $end
$scope module q2 $end
$var wire 1 " A $end
$var wire 1 # B $end
$var wire 1 $ C $end
$var wire 1 % D $end
$var wire 1 & Dn $end
$var wire 1 ! F $end
$var wire 1 ' o1 $end
$var wire 1 ( o2 $end
$var wire 1 ) o3 $end
$var wire 1 * o4 $end
$upscope $end
$upscope $end
$enddefinitions $end
#0
$dumpvars
0*
0)
1(
1'
1&
0%
0$
0#
0"
1!
$end
#20
1)
0&
0'
1%
#40
1&
1'
0(
0)
0%
1$
#60
0!
1*
0&
0'
1%
#80
0!
1*
1&
0)
0%
0$
1#
#100
1!
0*
1)
0&
1%
#120
0!
1*
1&
0)
0%
1$
#140
0&
1%
#160
1!
0*
1&
1'
1(
0%
0$
0#
1"
#180
0&
0'
1%
#200
1&
1'
0(
0%
1$
#220
0!
1*
0&
0'
1%
#240
1&
0%
0$
1#
#260
0&
1%
#280
1&
0%
1$
#300
0&
1%
