DISL Lab/Lab 3/q3/q3.v
module q3(F, A, B, C, D);
	input A, B, C, D;
	output F;
	nor n1(Dn, D, D);
	nor n2(o1, C, Dn);
	nor n3(o2, A, Dn);
	nor n4(o3, o1, o2);
	nor n5(F, o3, o3);
endmodule

DISL Lab/Lab 3/q3/q3_tb.v
`timescale 1ns/1ns
`include "q3.v"

module q3_tb();
reg A, B, C, D;
wire F;
q3 q3(F, A, B, C, D);
initial
begin
	$dumpfile("q3.vcd");
	$dumpvars(0, q3_tb);
	
	A = 1'b0; B = 1'b0; C = 1'b0; D = 1'b0;
	#20;
	A = 1'b0; B = 1'b0; C = 1'b0; D= 1'b1;
	#20;
	A = 1'b0; B = 1'b0; C = 1'b1; D = 1'b0;
	#20;
	A = 1'b0; B = 1'b0; C = 1'b1; D = 1'b1;
	#20;
	A = 1'b0; B = 1'b1; C = 1'b0; D = 1'b0;
	#20;
	A = 1'b0; B = 1'b1; C = 1'b0; D = 1'b1;
	#20;
	A = 1'b0; B = 1'b1; C = 1'b1; D = 1'b0;
	#20;
	A = 1'b0; B = 1'b1; C = 1'b1; D = 1'b1;
	#20;
	A = 1'b1; B = 1'b0; C = 1'b0; D = 1'b0;
	#20;
	A = 1'b1; B = 1'b0; C = 1'b0; D = 1'b1;
	#20;
	A = 1'b1; B = 1'b0; C = 1'b1; D = 1'b0;
	#20;
	A = 1'b1; B = 1'b0; C = 1'b1; D = 1'b1;
	#20;
	A = 1'b1; B = 1'b1; C = 1'b0; D = 1'b0;
	#20;
	A = 1'b1; B = 1'b1; C = 1'b0; D = 1'b1;
	#20;
	A = 1'b1; B = 1'b1; C = 1'b1; D = 1'b0;
	#20;
	A = 1'b1; B = 1'b1; C = 1'b1; D = 1'b1;
	#20;
	
	$display("please work");
end
endmodule

DISL Lab/Lab 3/q3/q3.vcd
$date
	Tue Aug 12 14:53:47 2025
$end
$version
	Icarus Verilog
$end
$timescale
	1ns
$end
$scope module q3_tb $end
$var wire 1 ! F $end
$var reg 1 " A $end
$var reg 1 # B $end
$var reg 1 $ C $end
$var reg 1 % D $end
$scope module q3 $end
$var wire 1 " A $end
$var wire 1 # B $end
$var wire 1 $ C $end
$var wire 1 % D $end
$var wire 1 & Dn $end
$var wire 1 ! F $end
$var wire 1 ' o1 $end
$var wire 1 ( o2 $end
$var wire 1 ) o3 $end
$upscope $end
$upscope $end
$enddefinitions $end
#0
$dumpvars
1)
0(
0'
1&
0%
0$
0#
0"
0!
$end
#20
1!
0)
1'
1(
0&
1%
#40
0!
1)
0(
1&
0'
0%
1$
#60
1!
0)
1(
0&
1%
#80
0!
1)
0(
1&
0'
0%
0$
1#
#100
1!
0)
1'
1(
0&
1%
#120
0!
1)
0(
1&
0'
0%
1$
#140
1!
0)
1(
0&
1%
#160
0!
1)
1&
0'
0(
0%
0$
0#
1"
#180
1!
0)
1'
0&
1%
#200
0!
1)
1&
0'
0%
1$
#220
0&
1%
#240
0!
1)
1&
0'
0%
0$
1#
#260
1!
0)
1'
0&
1%
#280
0!
1)
1&
0'
0%
1$
#300
0&
1%
