DISL Lab/Lab 2/q2/q2_b.v
module q2_b(F, A, B, C, D);
	input A, B, C, D;
	output F;
	not(An, A);
	not(Bn, B);
	not(Cn, C);
	not(Dn, D);
	or(o1, D, A, Bn);
	or(o2, Cn, An, B);
	or(o3, C, D, Bn);
	or(o4, An, B, Dn);
	and(F, o1, o2, o3, o4);
endmodule

DISL Lab/Lab 2/q2/q2_tb.v
`timescale 1ns/1ns
`include "q2_b.v"

module q2_tb();
reg A, B, C, D;
wire F;

q2_b q2(F, A, B, C, D);
initial
begin
	$dumpfile("q2_b.vcd");
	$dumpvars(0, q2_tb);
	
	A = 1'b0; B = 1'b0; C = 1'b0; D = 1'b0;
	#20;
	A = 1'b0; B = 1'b0; C = 1'b0; D= 1'b1;
	#20;
	A = 1'b0; B = 1'b0; C = 1'b1; D = 1'b0;
	#20;
	A = 1'b0; B = 1'b0; C = 1'b1; D = 1'b1;
	#20;
	A = 1'b0; B = 1'b1; C = 1'b0; D = 1'b0;
	#20;
	A = 1'b0; B = 1'b1; C = 1'b0; D = 1'b1;
	#20;
	A = 1'b0; B = 1'b1; C = 1'b1; D = 1'b0;
	#20;
	A = 1'b0; B = 1'b1; C = 1'b1; D = 1'b1;
	#20;
	A = 1'b1; B = 1'b0; C = 1'b0; D = 1'b0;
	#20;
	A = 1'b1; B = 1'b0; C = 1'b0; D = 1'b1;
	#20;
	A = 1'b1; B = 1'b0; C = 1'b1; D = 1'b0;
	#20;
	A = 1'b1; B = 1'b0; C = 1'b1; D = 1'b1;
	#20;
	A = 1'b1; B = 1'b1; C = 1'b0; D = 1'b0;
	#20;
	A = 1'b1; B = 1'b1; C = 1'b0; D = 1'b1;
	#20;
	A = 1'b1; B = 1'b1; C = 1'b1; D = 1'b0;
	#20;
	A = 1'b1; B = 1'b1; C = 1'b1; D = 1'b1;
	#20;
	
	$display("please work");
end
endmodule

DISL Lab/Lab 2/q2/q2_b.vcd
$date
	Tue Aug  5 15:50:12 2025
$end
$version
	Icarus Verilog
$end
$timescale
	1ns
$end
$scope module q2_tb $end
$var wire 1 ! F $end
$var reg 1 " A $end
$var reg 1 # B $end
$var reg 1 $ C $end
$var reg 1 % D $end
$scope module q2 $end
$var wire 1 " A $end
$var wire 1 & An $end
$var wire 1 # B $end
$var wire 1 ' Bn $end
$var wire 1 $ C $end
$var wire 1 ( Cn $end
$var wire 1 % D $end
$var wire 1 ) Dn $end
$var wire 1 ! F $end
$var wire 1 * o1 $end
$var wire 1 + o2 $end
$var wire 1 , o3 $end
$var wire 1 - o4 $end
$upscope $end
$upscope $end
$enddefinitions $end
#0
$dumpvars
1-
1,
1+
1*
1)
1(
1'
1&
0%
0$
0#
0"
1!
$end
#20
0)
1%
#40
1)
0(
0%
1$
#60
0)
1%
#80
0!
1)
0*
1(
0,
0'
0%
0$
1#
#100
1!
0)
1*
1,
1%
#120
0!
1)
0*
0(
0%
1$
#140
1!
0)
1*
1%
#160
1!
1)
1(
1'
1+
1-
0&
0%
0$
0#
1"
#180
0!
0-
0)
1%
#200
1-
0+
1)
0(
0%
1$
#220
0-
0)
1%
#240
1)
1(
0,
0'
1+
1-
0%
0$
1#
#260
1!
0)
1,
1%
#280
1)
0(
0%
1$
#300
0)
1%
