aiml_b/lab0/example.v
module example(a,b,c,d,y);
input a,b,c,d;
output y;
assign y = (~((a&b)|c)&d)&(((a&b)|c)|d);
endmodule

aiml_b/lab0/ex_tb.v
`timescale 1ns/1ps
`include "example.v"

module ex_tb;
    reg a_t, b_t, c_t, d_t;
    wire y_t;


    example uut (a_t, b_t,c_t,d_t,y_t);

    initial begin
        $dumpfile("ex_tb.vcd");
        $dumpvars(0, ex_tb);
a_t=0; b_t=0; c_t=0; d_t=0; #5;
a_t=0; b_t=0; c_t=0; d_t=1; #5;
a_t=0; b_t=0; c_t=1; d_t=0; #5;
a_t=0; b_t=0; c_t=1; d_t=1; #5;
a_t=0; b_t=1; c_t=0; d_t=0; #5;
a_t=0; b_t=1; c_t=0; d_t=1; #5;
a_t=0; b_t=1; c_t=1; d_t=0; #5;
a_t=0; b_t=1; c_t=1; d_t=1; #5;
a_t=1; b_t=0; c_t=0; d_t=0; #5;
a_t=1; b_t=0; c_t=0; d_t=1; #5;
a_t=1; b_t=0; c_t=1; d_t=0; #5;
a_t=1; b_t=0; c_t=1; d_t=1; #5;
a_t=1; b_t=1; c_t=0; d_t=0; #5;
a_t=1; b_t=1; c_t=0; d_t=1; #5;
a_t=1; b_t=1; c_t=1; d_t=0; #5;
a_t=1; b_t=1; c_t=1; d_t=1; #5;

        $display("Test complete");
        $finish;
    end
endmodule

lab1/ex_tb.vcd
$date
	Mon Jul 28 15:14:47 2025
$end
$version
	Icarus Verilog
$end
$timescale
	1ps
$end
$scope module ex_tb $end
$var wire 1 ! y_t $end
$var reg 1 " a_t $end
$var reg 1 # b_t $end
$var reg 1 $ c_t $end
$var reg 1 % d_t $end
$scope module uut $end
$var wire 1 " a $end
$var wire 1 # b $end
$var wire 1 $ c $end
$var wire 1 % d $end
$var wire 1 ! y $end
$upscope $end
$upscope $end
$enddefinitions $end
#0
$dumpvars
0%
0$
0#
0"
0!
$end
#5000
1!
1%
#10000
0!
0%
1$
#15000
1%
#20000
0%
0$
1#
#25000
1!
1%
#30000
0!
0%
1$
#35000
1%
#40000
0%
0$
0#
1"
#45000
1!
1%
#50000
0!
0%
1$
#55000
1%
#60000
0%
0$
1#
#65000
1%
#70000
0%
1$
#75000
1%
