aiml_b/lab4/full_adder.v
module full_adder(a, b, c, sum, carry);
    input a, b, c;
    output sum, carry;

    wire ab, bc, ac, temp_sum;

    // Sum = (a ⊕ b) ⊕ c
    xor x1(temp_sum, a, b);
    xor x2(sum, temp_sum, c);

    // Carry = (a & b) | (b & c) | (a & c)
    and a1(ab, a, b);
    and a2(bc, b, c);
    and a3(ac, a, c);
    or  o1(carry, ab, bc, ac);

endmodule

aiml_b/lab4/full_adder_tb.v
`timescale 1ns/1ps
`include "full_adder.v"
module full_adder_tb;
reg a_t,b_t,c_t;
wire sum_t,carry_t;
full_adder ara(a_t,b_t,c_t,sum_t,carry_t);
initial begin 
    $dumpfile("full_adder.vcd");
    $dumpvars(0,full_adder_tb);
        a_t = 0; b_t = 0; c_t = 0; #10;
        a_t = 0; b_t = 0; c_t = 1; #10;
        a_t = 0; b_t = 1; c_t = 0; #10;
        a_t = 0; b_t = 1; c_t = 1; #10;
        a_t = 1; b_t = 0; c_t = 0; #10;
        a_t = 1; b_t = 0; c_t = 1; #10;
        a_t = 1; b_t = 1; c_t = 0; #10;
        a_t = 1; b_t = 1; c_t = 1; #10;

$finish;
end
endmodule

aiml_b/lab4/full_adder.vcd
$date
	Mon Sep  1 02:54:11 2025
$end
$version
	Icarus Verilog
$end
$timescale
	1ps
$end
$scope module full_adder_tb $end
$var wire 1 ! sum_t $end
$var wire 1 " carry_t $end
$var reg 1 # a_t $end
$var reg 1 $ b_t $end
$var reg 1 % c_t $end
$scope module ara $end
$var wire 1 # a $end
$var wire 1 & ab $end
$var wire 1 ' ac $end
$var wire 1 $ b $end
$var wire 1 ( bc $end
$var wire 1 % c $end
$var wire 1 " carry $end
$var wire 1 ! sum $end
$var wire 1 ) temp_sum $end
$upscope $end
$upscope $end
$enddefinitions $end
#0
$dumpvars
0)
0(
0'
0&
0%
0$
0#
0"
0!
$end
#10000
1!
1%
#20000
1)
0%
1$
#30000
1"
0!
1(
1%
#40000
0"
1!
0(
0%
0$
1#
#50000
1"
0!
1'
1%
#60000
0'
0)
1&
0%
1$
#70000
1!
1(
1'
1%
